params/__init__.py
params/groups.json
telgamal/__init__.py
telgamal/elgamal.py
telgamal/player.py
telgamal/util.py
tests/__init__.py
tests/benchmarking.py
tests/elgamal_tests.py
tests/profiling.py
threshold_elgamal/__init__.py
threshold_elgamal/elgamal.py
threshold_elgamal/groups.json
threshold_elgamal/player.py
threshold_elgamal/util.py
threshold_elgamal-0.0.13.dist-info/METADATA
threshold_elgamal-0.0.13.dist-info/WHEEL
threshold_elgamal-0.0.13.dist-info/top_level.txt
threshold_elgamal-0.0.13.dist-info/RECORD
