Metadata-Version: 2.1
Name: threshold-elgamal
Version: 0.0.13
Summary: Threshold ElGamal cryptosystem
Home-page: https://threshold-elgamal.readthedocs.io/en/latest/index.html
Author: Katarina Boras
Author-email: katarina.boras2@outlook.com
License: UNKNOWN
Download-URL: https://gitlab.com/kboras/threshold-elgamal
Platform: UNKNOWN
